dff.v
//-----------------------------------------------------------------------------
//
// Title       : dff
// Design      : dffDesign_pet
// Author      : Mohammad Shazzad Hossain 
// Company     : 
//
//-----------------------------------------------------------------------------
//
// File        : c:\Users\shazz\Downloads\NTNU\MS_in_ESD\4th_semestar\Specialization_project\timer_design\dffDesign_pet\src\dff.v
// Generated   : Mon Mar 27 14:35:34 2023
// From        : interface description file
// By          : Itf2Vhdl ver. 1.22
//
//-----------------------------------------------------------------------------
//
// Description : Posetive ege triggered D flip flop. Used fro the initial design
//				 the counter.
//
//-----------------------------------------------------------------------------
`timescale 1 us / 1 ns

//{module {dff}}
module dff ( d, clk, pr_b , clr_b , q, q_b);

input d ;
wire d ; 
input clk ;
wire clk ;
input pr_b;
wire pr_b;
input clr_b;
wire clr_b;
output q ;
wire q ;
output q_b ;
wire q_b ;

//}} End of automatically maintained section
wire w1, w2, s, r; 	

//this design can be found in the moris meno book in sequential design chapter and also in digital principle and design book
nand G1 (w1,w2,s,pr_b);
nand G2 (s,clk,w1,clr_b);
nand G3 (r,s,w2,clk);
nand G4 (w2,d,r,clr_b);
nand G5 (q,s,q_b,pr_b);
nand G6 (q_b,r,q,clr_b);


endmodule

GrayCounter_4b.sv
`timescale 1us/1ns

module GrayCounter_4b (cten,clk,prs,clr,out,tc);
	
	input wire cten;
	input wire clk;
	input wire prs;
	input wire clr;
	output wire [3:0] out;
	output wire tc;
	
	wire [3:0] connect_q;
	wire [3:0] connect_qb;
		
	wire [14:0] andout;
	wire [3:0] orout;
	wire norout; 
	//wire [1:0] xnorout;
	//wire  	   xorout;	
	
	//comibinational feedback logic for 1st dff	D3
	and G1 (andout[0],connect_q[2],connect_qb[1],connect_qb[0]);
	and G2 (andout[1],connect_q[3],connect_q[0]);
	and G3 (andout[2],connect_q[3],connect_q[1]);
	or  G4 (orout[0],andout[0],andout[1],andout[2]); 
	
	//comibinational feedback logic for 2nd dff	D2
	and G5 (andout[3],connect_qb[3],connect_q[1],connect_qb[0]);
	and G6 (andout[4],connect_q[2],connect_qb[1]);
	and G7 (andout[5],connect_q[2],connect_q[0]);
	or  G8 (orout[1],andout[3],andout[4],andout[5]);
	
	//comibinational feedback logic for 3rd dff	D1 
	and G9 (andout[6],connect_q[1],connect_qb[0]);
	and G10 (andout[10],connect_qb[3],connect_qb[2],connect_q[0]);
	//xnor G10 (xnorout[0],connect_q[3],connect_q[2]);
	and G11 (andout[7],connect_q[3],connect_q[2],connect_q[0]);
	or  G12 (orout[2],andout[6],andout[7],andout[10]);
	
	//comibinational feedback logic for 4th dff	D0
	//xnor G13 (xnorout[1],connect_q[3],connect_q[1]); 
	and	G13 (andout[11],connect_qb[3],connect_qb[2],connect_qb[1]);
	and G14 (andout[8],connect_q[3],connect_q[2],connect_qb[1]);
	//xor G15	(xorout,connect_q[3],connect_q[1]);	 
	and G16 (andout[9],connect_qb[3],connect_q[2],connect_q[1]);
	and G15 (andout[12],connect_q[3],connect_qb[2],connect_q[1]);
	or  G17 (orout[3],andout[8],andout[9],andout[11],andout[12]);
	
	// clock enable using cten 
	and G18 (andout[13],cten,clk);
	
	dff D0 (.clk(andout[13]),.pr_b(prs),.clr_b(clr),.d(orout[3]),.q(connect_q[0]),.q_b(connect_qb[0]));
	dff D1 (.clk(andout[13]),.pr_b(prs),.clr_b(clr),.d(orout[2]),.q(connect_q[1]),.q_b(connect_qb[1]));
	dff D2 (.clk(andout[13]),.pr_b(prs),.clr_b(clr),.d(orout[1]),.q(connect_q[2]),.q_b(connect_qb[2]));
	dff D3 (.clk(andout[13]),.pr_b(prs),.clr_b(clr),.d(orout[0]),.q(connect_q[3]),.q_b(connect_qb[3]));
	
		
	assign out = connect_q;
	nor G19 (norout,connect_q[0],connect_q[1],connect_q[2]);
	and G20 (andout[14], norout,connect_q[3]);
	assign tc = andout[14];

	
endmodule

counter.sv
`timescale 1us/1ns

module counter (en,clk,prs,clr,out,tc, count_triger);
	input wire en;
	input wire clk;
	input wire prs;
	input wire clr;
	output wire [7:0] out;
	output wire tc;
	output wire count_triger;
	
	wire tctonc;
	

	
	//RippleCounter_4b RC1 (.clk(clk), .prs(prs), .clr(clr), .out(out[3:0]), .tc(tctonc));
	//RippleCounter_4b RC2 (.clk(tctonc), .prs(prs), .clr(clr), .out(out[7:4]),.tc(tc));
	GrayCounter_4b GC1 (.cten(en),.clk(clk),.prs(prs),.clr(clr),.out(out[3:0]),.tc(tcronc));
	GrayCounter_4b GC2 (.cten(tctonc),.clk(clk),.prs(prs),.clr(clr),.out(out[7:4]),.tc(tc)); 
	
	assign count_triger = tc;
	/*
	//fro gray to binary conversion 
	wire [7:0] wout;
	wire [6:0] xorout;
	
	//fro gray to binary conversion
	generate
		genvar i;
		for (i=7;i<=0;i--) begin
			if (i == 7) begin
				assign out [i] = wout [i];
			end else if (i == 6) begin
				xor gi (xorout[i], wout[i], wout[i+1]);
				assign  out [i] = xorout [i];
			end else begin
				xor gi (xorout[i], wout[i], xorout[i+1]);
				assign  out [i] = xorout [i];
			end
		end
		
	endgenerate
*/	
	
endmodule

dffDesign_pet/src/counter_tb.sv
`timescale 1ns/1ps

module counter_tb;
	reg  en, clk, prs, clr; 
	wire [7:0] out;
	wire tc,count_triger;
	
	counter dut_counter (.en(en),.clk(clk), .prs(prs),.clr(clr),.out(out),.tc(tc),.count_triger(count_triger));
	
	always begin
		#2 clk = ~clk;
	end
	initial begin
		$dumpfile ("dump.vcd");
		$dumpvars(0,counter_tb);
		en = 0;
		clk = 0;
		prs = 1;
		clr = 0;
		$monitor ("clk time= ", $time, "out=%d, tc=%d, clr= %b", out,tc,clr);
		#4 prs = 1; clr = 1; en = 1;
		
		#4000	$finish;
		
	end
		
endmodule

dffDesign_pet/dump.vcd
$date
Sat May 20 09:30:24 2023
$end
$version
Aldec HDL Simulator Version 13.0.376
$end
$timescale
1 ps
$end

$scope module counter_tb $end
$var wire 1 ! out [7] $end
$var wire 1 " out [6] $end
$var wire 1 # out [5] $end
$var wire 1 $ out [4] $end
$var wire 1 % out [3] $end
$var wire 1 & out [2] $end
$var wire 1 ' out [1] $end
$var wire 1 ( out [0] $end
$var wire 1 ) tc $end
$var wire 1 * count_triger $end
$var reg 1 + en $end
$var reg 1 , clk $end
$var reg 1 - prs $end
$var reg 1 . clr $end

$scope module dut_counter $end
$var wire 1 / en $end
$var wire 1 0 clk $end
$var wire 1 1 prs $end
$var wire 1 2 clr $end
$var wire 1 ! out [7] $end
$var wire 1 " out [6] $end
$var wire 1 # out [5] $end
$var wire 1 $ out [4] $end
$var wire 1 % out [3] $end
$var wire 1 & out [2] $end
$var wire 1 ' out [1] $end
$var wire 1 ( out [0] $end
$var wire 1 ) tc $end
$var wire 1 * count_triger $end
$var wire 1 3 tctonc $end
$var wire 1 4 tcronc $end

$scope module GC1 $end
$var wire 1 / cten $end
$var wire 1 0 clk $end
$var wire 1 1 prs $end
$var wire 1 2 clr $end
$var wire 1 % out [3] $end
$var wire 1 & out [2] $end
$var wire 1 ' out [1] $end
$var wire 1 ( out [0] $end
$var wire 1 4 tc $end
$var wire 1 5 connect_q [3] $end
$var wire 1 6 connect_q [2] $end
$var wire 1 7 connect_q [1] $end
$var wire 1 8 connect_q [0] $end
$var wire 1 9 connect_qb [3] $end
$var wire 1 : connect_qb [2] $end
$var wire 1 ; connect_qb [1] $end
$var wire 1 < connect_qb [0] $end
$var wire 1 = andout [14] $end
$var wire 1 > andout [13] $end
$var wire 1 ? andout [12] $end
$var wire 1 @ andout [11] $end
$var wire 1 A andout [10] $end
$var wire 1 B andout [9] $end
$var wire 1 C andout [8] $end
$var wire 1 D andout [7] $end
$var wire 1 E andout [6] $end
$var wire 1 F andout [5] $end
$var wire 1 G andout [4] $end
$var wire 1 H andout [3] $end
$var wire 1 I andout [2] $end
$var wire 1 J andout [1] $end
$var wire 1 K andout [0] $end
$var wire 1 L orout [3] $end
$var wire 1 M orout [2] $end
$var wire 1 N orout [1] $end
$var wire 1 O orout [0] $end
$var wire 1 P norout $end

$scope module D0 $end
$var wire 1 L d $end
$var wire 1 > clk $end
$var wire 1 1 pr_b $end
$var wire 1 2 clr_b $end
$var wire 1 8 q $end
$var wire 1 < q_b $end
$var wire 1 Q w1 $end
$var wire 1 R w2 $end
$var wire 1 S s $end
$var wire 1 T r $end
$upscope $end


$scope module D1 $end
$var wire 1 M d $end
$var wire 1 > clk $end
$var wire 1 1 pr_b $end
$var wire 1 2 clr_b $end
$var wire 1 7 q $end
$var wire 1 ; q_b $end
$var wire 1 U w1 $end
$var wire 1 V w2 $end
$var wire 1 W s $end
$var wire 1 X r $end
$upscope $end


$scope module D2 $end
$var wire 1 N d $end
$var wire 1 > clk $end
$var wire 1 1 pr_b $end
$var wire 1 2 clr_b $end
$var wire 1 6 q $end
$var wire 1 : q_b $end
$var wire 1 Y w1 $end
$var wire 1 Z w2 $end
$var wire 1 [ s $end
$var wire 1 \ r $end
$upscope $end


$scope module D3 $end
$var wire 1 O d $end
$var wire 1 > clk $end
$var wire 1 1 pr_b $end
$var wire 1 2 clr_b $end
$var wire 1 5 q $end
$var wire 1 9 q_b $end
$var wire 1 ] w1 $end
$var wire 1 ^ w2 $end
$var wire 1 _ s $end
$var wire 1 ` r $end
$upscope $end

$upscope $end


$scope module GC2 $end
$var wire 1 3 cten $end
$var wire 1 0 clk $end
$var wire 1 1 prs $end
$var wire 1 2 clr $end
$var wire 1 ! out [3] $end
$var wire 1 " out [2] $end
$var wire 1 # out [1] $end
$var wire 1 $ out [0] $end
$var wire 1 ) tc $end
$var wire 1 a connect_q [3] $end
$var wire 1 b connect_q [2] $end
$var wire 1 c connect_q [1] $end
$var wire 1 d connect_q [0] $end
$var wire 1 e connect_qb [3] $end
$var wire 1 f connect_qb [2] $end
$var wire 1 g connect_qb [1] $end
$var wire 1 h connect_qb [0] $end
$var wire 1 i andout [14] $end
$var wire 1 j andout [13] $end
$var wire 1 k andout [12] $end
$var wire 1 l andout [11] $end
$var wire 1 m andout [10] $end
$var wire 1 n andout [9] $end
$var wire 1 o andout [8] $end
$var wire 1 p andout [7] $end
$var wire 1 q andout [6] $end
$var wire 1 r andout [5] $end
$var wire 1 s andout [4] $end
$var wire 1 t andout [3] $end
$var wire 1 u andout [2] $end
$var wire 1 v andout [1] $end
$var wire 1 w andout [0] $end
$var wire 1 x orout [3] $end
$var wire 1 y orout [2] $end
$var wire 1 z orout [1] $end
$var wire 1 { orout [0] $end
$var wire 1 | norout $end

$scope module D0 $end
$var wire 1 x d $end
$var wire 1 j clk $end
$var wire 1 1 pr_b $end
$var wire 1 2 clr_b $end
$var wire 1 d q $end
$var wire 1 h q_b $end
$var wire 1 } w1 $end
$var wire 1 ~ w2 $end
$var wire 1 !! s $end
$var wire 1 "! r $end
$upscope $end


$scope module D1 $end
$var wire 1 y d $end
$var wire 1 j clk $end
$var wire 1 1 pr_b $end
$var wire 1 2 clr_b $end
$var wire 1 c q $end
$var wire 1 g q_b $end
$var wire 1 #! w1 $end
$var wire 1 $! w2 $end
$var wire 1 %! s $end
$var wire 1 &! r $end
$upscope $end


$scope module D2 $end
$var wire 1 z d $end
$var wire 1 j clk $end
$var wire 1 1 pr_b $end
$var wire 1 2 clr_b $end
$var wire 1 b q $end
$var wire 1 f q_b $end
$var wire 1 '! w1 $end
$var wire 1 (! w2 $end
$var wire 1 )! s $end
$var wire 1 *! r $end
$upscope $end


$scope module D3 $end
$var wire 1 { d $end
$var wire 1 j clk $end
$var wire 1 1 pr_b $end
$var wire 1 2 clr_b $end
$var wire 1 a q $end
$var wire 1 e q_b $end
$var wire 1 +! w1 $end
$var wire 1 ,! w2 $end
$var wire 1 -! s $end
$var wire 1 .! r $end
$upscope $end

$upscope $end

$upscope $end

$upscope $end

$enddefinitions $end
$dumpvars
0!
0"
0#
0$
0%
0&
0'
0(
0)
0*
0+
0,
1-
0.
0/
00
11
02
z3
04
05
06
07
08
19
1:
1;
1<
0=
0>
0?
1@
0A
0B
0C
0D
0E
0F
0G
0H
0I
0J
0K
1L
0M
0N
0O
1P
0Q
1R
1S
1T
0U
1V
1W
1X
0Y
1Z
1[
1\
0]
1^
1_
1`
0a
0b
0c
0d
1e
1f
1g
1h
0i
0j
0k
1l
0m
0n
0o
0p
0q
0r
0s
0t
0u
0v
0w
1x
0y
0z
0{
1|
0}
1~
1!!
1"!
0#!
1$!
1%!
1&!
0'!
1(!
1)!
1*!
0+!
1,!
1-!
1.!
$end
#2000
1,
10
xj
x.!
x*!
x&!
x"!
#4000
1.
1+
0,
00
1/
12
x~
0R
0j
1.!
1*!
1&!
1"!
1Q
x}
0~
1}
#6000
1,
10
xj
1>
0`
0\
0X
0S
x.!
x*!
x&!
x!!
xd
18
x$
1(
0<
0P
1A
xh
x|
xm
xy
1M
x$!
x#!
x%!
xc
x#
xg
xq
xt
xz
xl
xx
x(!
x'!
x~
x"!
x}
x)!
xb
x"
xf
xn
xr
xs
xw
x{
x,!
x+!
x-!
xa
x!
xe
xi
xk
xo
xp
xu
xv
x)
x*
#8000
0,
00
0j
0>
1`
1\
1X
1S
1.!
1-!
1*!
1)!
1&!
1%!
1"!
1!!
0V
1U
#10000
1,
10
xj
1>
0`
0\
0W
0S
x.!
x-!
x*!
x)!
x&!
x%!
x"!
x!!
17
1'
0;
0@
0L
1R
#12000
0,
00
0j
0>
1`
1\
1W
1S
1.!
1-!
1*!
1)!
1&!
1%!
1"!
1!!
0Q
#14000
1,
10
xj
1>
0`
0\
0W
0T
x.!
x-!
x*!
x)!
x&!
x%!
x"!
x!!
1<
08
1E
1H
0(
1N
0A
#16000
0,
00
0j
0>
1`
1\
1W
1T
1.!
1-!
1*!
1)!
1&!
1%!
1"!
1!!
0Z
1Y
#18000
1,
10
xj
1>
0`
0[
0W
0T
x.!
x-!
x*!
x)!
x&!
x%!
x"!
x!!
16
1&
0:
1B
1L
#20000
0,
00
0j
0>
1`
1[
1W
1T
1.!
1-!
1*!
1)!
1&!
1%!
1"!
1!!
0R
1Q
#22000
1,
10
xj
1>
0`
0[
0W
0S
x.!
x-!
x*!
x)!
x&!
x%!
x"!
x!!
18
1(
0<
1F
0E
0H
0M
1V
#24000
0,
00
0j
0>
1`
1[
1W
1S
1.!
1-!
1*!
1)!
1&!
1%!
1"!
1!!
0U
#26000
1,
10
xj
1>
0`
0[
0X
0S
x.!
x-!
x*!
x)!
x&!
x%!
x"!
x!!
1;
07
1G
0'
0B
0L
1R
#28000
0,
00
0j
0>
1`
1[
1X
1S
1.!
1-!
1*!
1)!
1&!
1%!
1"!
1!!
0Q
#30000
1,
10
xj
1>
0`
0[
0X
0T
x.!
x-!
x*!
x)!
x&!
x%!
x"!
x!!
1<
08
1K
0(
1O
0F
#32000
0,
00
0j
0>
1`
1[
1X
1T
1.!
1-!
1*!
1)!
1&!
1%!
1"!
1!!
0^
1]
#34000
1,
10
xj
1>
0_
0[
0X
0T
x.!
x-!
x*!
x)!
x&!
x%!
x"!
x!!
15
1%
09
1C
1L
#36000
0,
00
0j
0>
1_
1[
1X
1T
1.!
1-!
1*!
1)!
1&!
1%!
1"!
1!!
0R
1Q
#38000
1,
10
xj
1>
0_
0[
0X
0S
x.!
x-!
x*!
x)!
x&!
x%!
x"!
x!!
18
1(
0<
1D
1F
1J
1M
0K
#40000
0,
00
0j
0>
1_
1[
1X
1S
1.!
1-!
1*!
1)!
1&!
1%!
1"!
1!!
0V
1U
#42000
1,
10
xj
1>
0_
0[
0W
0S
x.!
x-!
x*!
x)!
x&!
x%!
x"!
x!!
17
1'
0;
1I
0C
0G
0L
1R
#44000
0,
00
0j
0>
1_
1[
1W
1S
1.!
1-!
1*!
1)!
1&!
1%!
1"!
1!!
0Q
#46000
1,
10
xj
1>
0_
0[
0W
0T
x.!
x-!
x*!
x)!
x&!
x%!
x"!
x!!
1<
08
1E
0(
0D
0F
0J
0N
1Z
#48000
0,
00
0j
0>
1_
1[
1W
1T
1.!
1-!
1*!
1)!
1&!
1%!
1"!
1!!
0Y
#50000
1,
10
xj
1>
0_
0\
0W
0T
x.!
x-!
x*!
x)!
x&!
x%!
x"!
x!!
1:
06
1?
0&
1L
#52000
0,
00
0j
0>
1_
1\
1W
1T
1.!
1-!
1*!
1)!
1&!
1%!
1"!
1!!
0R
1Q
#54000
1,
10
xj
1>
0_
0\
0W
0S
x.!
x-!
x*!
x)!
x&!
x%!
x"!
x!!
18
1(
0<
1J
0E
0M
1V
#56000
0,
00
0j
0>
1_
1\
1W
1S
1.!
1-!
1*!
1)!
1&!
1%!
1"!
1!!
0U
#58000
1,
10
xj
1>
0_
0\
0X
0S
x.!
x-!
x*!
x)!
x&!
x%!
x"!
x!!
1;
07
0'
0?
0I
0L
1R
#60000
0,
00
0j
0>
1_
1\
1X
1S
1.!
1-!
1*!
1)!
1&!
1%!
1"!
1!!
0Q
#62000
1,
10
xj
1>
0_
0\
0X
0T
x.!
x-!
x*!
x)!
x&!
x%!
x"!
x!!
1<
08
0(
1P
0J
0O
1=
14
1^
#64000
0,
00
0j
0>
1_
1\
1X
1T
1.!
1-!
1*!
1)!
1&!
1%!
1"!
1!!
0]
#66000
1,
10
xj
1>
0`
0\
0X
0T
x.!
x-!
x*!
x)!
x&!
x%!
x"!
x!!
19
05
1@
0%
1L
0=
04
#68000
0,
00
0j
0>
1`
1\
1X
1T
1.!
1-!
1*!
1)!
1&!
1%!
1"!
1!!
0R
1Q
#70000
1,
10
xj
1>
0`
0\
0X
0S
x.!
x-!
x*!
x)!
x&!
x%!
x"!
x!!
18
1(
0<
0P
1A
1M
#72000
0,
00
0j
0>
1`
1\
1X
1S
1.!
1-!
1*!
1)!
1&!
1%!
1"!
1!!
0V
1U
#74000
1,
10
xj
1>
0`
0\
0W
0S
x.!
x-!
x*!
x)!
x&!
x%!
x"!
x!!
17
1'
0;
0@
0L
1R
#76000
0,
00
0j
0>
1`
1\
1W
1S
1.!
1-!
1*!
1)!
1&!
1%!
1"!
1!!
0Q
#78000
1,
10
xj
1>
0`
0\
0W
0T
x.!
x-!
x*!
x)!
x&!
x%!
x"!
x!!
1<
08
1E
1H
0(
1N
0A
#80000
0,
00
0j
0>
1`
1\
1W
1T
1.!
1-!
1*!
1)!
1&!
1%!
1"!
1!!
0Z
1Y
#82000
1,
10
xj
1>
0`
0[
0W
0T
x.!
x-!
x*!
x)!
x&!
x%!
x"!
x!!
16
1&
0:
1B
1L
#84000
0,
00
0j
0>
1`
1[
1W
1T
1.!
1-!
1*!
1)!
1&!
1%!
1"!
1!!
0R
1Q
#86000
1,
10
xj
1>
0`
0[
0W
0S
x.!
x-!
x*!
x)!
x&!
x%!
x"!
x!!
18
1(
0<
1F
0E
0H
0M
1V
#88000
0,
00
0j
0>
1`
1[
1W
1S
1.!
1-!
1*!
1)!
1&!
1%!
1"!
1!!
0U
#90000
1,
10
xj
1>
0`
0[
0X
0S
x.!
x-!
x*!
x)!
x&!
x%!
x"!
x!!
1;
07
1G
0'
0B
0L
1R
#92000
0,
00
0j
0>
1`
1[
1X
1S
1.!
1-!
1*!
1)!
1&!
1%!
1"!
1!!
0Q
#94000
1,
10
xj
1>
0`
0[
0X
0T
x.!
x-!
x*!
x)!
x&!
x%!
x"!
x!!
1<
08
1K
0(
1O
0F
#96000
0,
00
0j
0>
1`
1[
1X
1T
1.!
1-!
1*!
1)!
1&!
1%!
1"!
1!!
0^
1]
#98000
1,
10
xj
1>
0_
0[
0X
0T
x.!
x-!
x*!
x)!
x&!
x%!
x"!
x!!
15
1%
09
1C
1L
#100000
0,
00
0j
0>
1_
1[
1X
1T
1.!
1-!
1*!
1)!
1&!
1%!
1"!
1!!
0R
1Q
#102000
1,
10
xj
1>
0_
0[
0X
0S
x.!
x-!
x*!
x)!
x&!
x%!
x"!
x!!
18
1(
0<
1D
1F
1J
1M
0K
#104000
0,
00
0j
0>
1_
1[
1X
1S
1.!
1-!
1*!
1)!
1&!
1%!
1"!
1!!
0V
1U
#106000
1,
10
xj
1>
0_
0[
0W
0S
x.!
x-!
x*!
x)!
x&!
x%!
x"!
x!!
17
1'
0;
1I
0C
0G
0L
1R
#108000
0,
00
0j
0>
1_
1[
1W
1S
1.!
1-!
1*!
1)!
1&!
1%!
1"!
1!!
0Q
#110000
1,
10
xj
1>
0_
0[
0W
0T
x.!
x-!
x*!
x)!
x&!
x%!
x"!
x!!
1<
08
1E
0(
0D
0F
0J
0N
1Z
#112000
0,
00
0j
0>
1_
1[
1W
1T
1.!
1-!
1*!
1)!
1&!
1%!
1"!
1!!
0Y
#114000
1,
10
xj
1>
0_
0\
0W
0T
x.!
x-!
x*!
x)!
x&!
x%!
x"!
x!!
1:
06
1?
0&
1L
#116000
0,
00
0j
0>
1_
1\
1W
1T
1.!
1-!
1*!
1)!
1&!
1%!
1"!
1!!
0R
1Q
#118000
1,
10
xj
1>
0_
0\
0W
0S
x.!
x-!
x*!
x)!
x&!
x%!
x"!
x!!
18
1(
0<
1J
0E
0M
1V
#120000
0,
00
0j
0>
1_
1\
1W
1S
1.!
1-!
1*!
1)!
1&!
1%!
1"!
1!!
0U
#122000
1,
10
xj
1>
0_
0\
0X
0S
x.!
x-!
x*!
x)!
x&!
x%!
x"!
x!!
1;
07
0'
0?
0I
0L
1R
#124000
0,
00
0j
0>
1_
1\
1X
1S
1.!
1-!
1*!
1)!
1&!
1%!
1"!
1!!
0Q
#126000
1,
10
xj
1>
0_
0\
0X
0T
x.!
x-!
x*!
x)!
x&!
x%!
x"!
x!!
1<
08
0(
1P
0J
0O
1=
14
1^
#128000
0,
00
0j
0>
1_
1\
1X
1T
1.!
1-!
1*!
1)!
1&!
1%!
1"!
1!!
0]
#130000
1,
10
xj
1>
0`
0\
0X
0T
x.!
x-!
x*!
x)!
x&!
x%!
x"!
x!!
19
05
1@
0%
1L
0=
04
#132000
0,
00
0j
0>
1`
1\
1X
1T
1.!
1-!
1*!
1)!
1&!
1%!
1"!
1!!
0R
1Q
#134000
1,
10
xj
1>
0`
0\
0X
0S
x.!
x-!
x*!
x)!
x&!
x%!
x"!
x!!
18
1(
0<
0P
1A
1M
#136000
0,
00
0j
0>
1`
1\
1X
1S
1.!
1-!
1*!
1)!
1&!
1%!
1"!
1!!
0V
1U
#138000
1,
10
xj
1>
0`
0\
0W
0S
x.!
x-!
x*!
x)!
x&!
x%!
x"!
x!!
17
1'
0;
0@
0L
1R
#140000
0,
00
0j
0>
1`
1\
1W
1S
1.!
1-!
1*!
1)!
1&!
1%!
1"!
1!!
0Q
#142000
1,
10
xj
1>
0`
0\
0W
0T
x.!
x-!
x*!
x)!
x&!
x%!
x"!
x!!
1<
08
1E
1H
0(
1N
0A
#144000
0,
00
0j
0>
1`
1\
1W
1T
1.!
1-!
1*!
1)!
1&!
1%!
1"!
1!!
0Z
1Y
#146000
1,
10
xj
1>
0`
0[
0W
0T
x.!
x-!
x*!
x)!
x&!
x%!
x"!
x!!
16
1&
0:
1B
1L
#148000
0,
00
0j
0>
1`
1[
1W
1T
1.!
1-!
1*!
1)!
1&!
1%!
1"!
1!!
0R
1Q
#150000
1,
10
xj
1>
0`
0[
0W
0S
x.!
x-!
x*!
x)!
x&!
x%!
x"!
x!!
18
1(
0<
1F
0E
0H
0M
1V
#152000
0,
00
0j
0>
1`
1[
1W
1S
1.!
1-!
1*!
1)!
1&!
1%!
1"!
1!!
0U
#154000
1,
10
xj
1>
0`
0[
0X
0S
x.!
x-!
x*!
x)!
x&!
x%!
x"!
x!!
1;
07
1G
0'
0B
0L
1R
#156000
0,
00
0j
0>
1`
1[
1X
1S
1.!
1-!
1*!
1)!
1&!
1%!
1"!
1!!
0Q
#158000
1,
10
xj
1>
0`
0[
0X
0T
x.!
x-!
x*!
x)!
x&!
x%!
x"!
x!!
1<
08
1K
0(
1O
0F
#160000
0,
00
0j
0>
1`
1[
1X
1T
1.!
1-!
1*!
1)!
1&!
1%!
1"!
1!!
0^
1]
#162000
1,
10
xj
1>
0_
0[
0X
0T
x.!
x-!
x*!
x)!
x&!
x%!
x"!
x!!
15
1%
09
1C
1L
#164000
0,
00
0j
0>
1_
1[
1X
1T
1.!
1-!
1*!
1)!
1&!
1%!
1"!
1!!
0R
1Q
#166000
1,
10
xj
1>
0_
0[
0X
0S
x.!
x-!
x*!
x)!
x&!
x%!
x"!
x!!
18
1(
0<
1D
1F
1J
1M
0K
#168000
0,
00
0j
0>
1_
1[
1X
1S
1.!
1-!
1*!
1)!
1&!
1%!
1"!
1!!
0V
1U
#170000
1,
10
xj
1>
0_
0[
0W
0S
x.!
x-!
x*!
x)!
x&!
x%!
x"!
x!!
17
1'
0;
1I
0C
0G
0L
1R
#172000
0,
00
0j
0>
1_
1[
1W
1S
1.!
1-!
1*!
1)!
1&!
1%!
1"!
1!!
0Q
#174000
1,
10
xj
1>
0_
0[
0W
0T
x.!
x-!
x*!
x)!
x&!
x%!
x"!
x!!
1<
08
1E
0(
0D
0F
0J
0N
1Z
#176000
0,
00
0j
0>
1_
1[
1W
1T
1.!
1-!
1*!
1)!
1&!
1%!
1"!
1!!
0Y
#178000
1,
10
xj
1>
0_
0\
0W
0T
x.!
x-!
x*!
x)!
x&!
x%!
x"!
x!!
1:
06
1?
0&
1L
#180000
0,
00
0j
0>
1_
1\
1W
1T
1.!
1-!
1*!
1)!
1&!
1%!
1"!
1!!
0R
1Q
#182000
1,
10
xj
1>
0_
0\
0W
0S
x.!
x-!
x*!
x)!
x&!
x%!
x"!
x!!
18
1(
0<
1J
0E
0M
1V
#184000
0,
00
0j
0>
1_
1\
1W
1S
1.!
1-!
1*!
1)!
1&!
1%!
1"!
1!!
0U
#186000
1,
10
xj
1>
0_
0\
0X
0S
x.!
x-!
x*!
x)!
x&!
x%!
x"!
x!!
1;
07
0'
0?
0I
0L
1R
#188000
0,
00
0j
0>
1_
1\
1X
1S
1.!
1-!
1*!
1)!
1&!
1%!
1"!
1!!
0Q
#190000
1,
10
xj
1>
0_
0\
0X
0T
x.!
x-!
x*!
x)!
x&!
x%!
x"!
x!!
1<
08
0(
1P
0J
0O
1=
14
1^
#192000
0,
00
0j
0>
1_
1\
1X
1T
1.!
1-!
1*!
1)!
1&!
1%!
1"!
1!!
0]
#194000
1,
10
xj
1>
0`
0\
0X
0T
x.!
x-!
x*!
x)!
x&!
x%!
x"!
x!!
19
05
1@
0%
1L
0=
04
#196000
0,
00
0j
0>
1`
1\
1X
1T
1.!
1-!
1*!
1)!
1&!
1%!
1"!
1!!
0R
1Q
#198000
1,
10
xj
1>
0`
0\
0X
0S
x.!
x-!
x*!
x)!
x&!
x%!
x"!
x!!
18
1(
0<
0P
1A
1M
#200000
0,
00
0j
0>
1`
1\
1X
1S
1.!
1-!
1*!
1)!
1&!
1%!
1"!
1!!
0V
1U
#202000
1,
10
xj
1>
0`
0\
0W
0S
x.!
x-!
x*!
x)!
x&!
x%!
x"!
x!!
17
1'
0;
0@
0L
1R
#204000
0,
00
0j
0>
1`
1\
1W
1S
1.!
1-!
1*!
1)!
1&!
1%!
1"!
1!!
0Q
#206000
1,
10
xj
1>
0`
0\
0W
0T
x.!
x-!
x*!
x)!
x&!
x%!
x"!
x!!
1<
08
1E
1H
0(
1N
0A
#208000
0,
00
0j
0>
1`
1\
1W
1T
1.!
1-!
1*!
1)!
1&!
1%!
1"!
1!!
0Z
1Y
#210000
1,
10
xj
1>
0`
0[
0W
0T
x.!
x-!
x*!
x)!
x&!
x%!
x"!
x!!
16
1&
0:
1B
1L
#212000
0,
00
0j
0>
1`
1[
1W
1T
1.!
1-!
1*!
1)!
1&!
1%!
1"!
1!!
0R
1Q
#214000
1,
10
xj
1>
0`
0[
0W
0S
x.!
x-!
x*!
x)!
x&!
x%!
x"!
x!!
18
1(
0<
1F
0E
0H
0M
1V
#216000
0,
00
0j
0>
1`
1[
1W
1S
1.!
1-!
1*!
1)!
1&!
1%!
1"!
1!!
0U
#218000
1,
10
xj
1>
0`
0[
0X
0S
x.!
x-!
x*!
x)!
x&!
x%!
x"!
x!!
1;
07
1G
0'
0B
0L
1R
#220000
0,
00
0j
0>
1`
1[
1X
1S
1.!
1-!
1*!
1)!
1&!
1%!
1"!
1!!
0Q
#222000
1,
10
xj
1>
0`
0[
0X
0T
x.!
x-!
x*!
x)!
x&!
x%!
x"!
x!!
1<
08
1K
0(
1O
0F
#224000
0,
00
0j
0>
1`
1[
1X
1T
1.!
1-!
1*!
1)!
1&!
1%!
1"!
1!!
0^
1]
#226000
1,
10
xj
1>
0_
0[
0X
0T
x.!
x-!
x*!
x)!
x&!
x%!
x"!
x!!
15
1%
09
1C
1L
#228000
0,
00
0j
0>
1_
1[
1X
1T
1.!
1-!
1*!
1)!
1&!
1%!
1"!
1!!
0R
1Q
#230000
1,
10
xj
1>
0_
0[
0X
0S
x.!
x-!
x*!
x)!
x&!
x%!
x"!
x!!
18
1(
0<
1D
1F
1J
1M
0K
#232000
0,
00
0j
0>
1_
1[
1X
1S
1.!
1-!
1*!
1)!
1&!
1%!
1"!
1!!
0V
1U
#234000
1,
10
xj
1>
0_
0[
0W
0S
x.!
x-!
x*!
x)!
x&!
x%!
x"!
x!!
17
1'
0;
1I
0C
0G
0L
1R
#236000
0,
00
0j
0>
1_
1[
1W
1S
1.!
1-!
1*!
1)!
1&!
1%!
1"!
1!!
0Q
#238000
1,
10
xj
1>
0_
0[
0W
0T
x.!
x-!
x*!
x)!
x&!
x%!
x"!
x!!
1<
08
1E
0(
0D
0F
0J
0N
1Z
#240000
0,
00
0j
0>
1_
1[
1W
1T
1.!
1-!
1*!
1)!
1&!
1%!
1"!
1!!
0Y
#242000
1,
10
xj
1>
0_
0\
0W
0T
x.!
x-!
x*!
x)!
x&!
x%!
x"!
x!!
1:
06
1?
0&
1L
