timer_design/dffDesign_pet/src/ms_dff.sv
`timescale 1us/1ns

module ms_dff (d, clk, ce, clr, prs, q , q_b);  
	input wire d;
	input wire clk;
	input wire clr;
	input wire ce;
	input wire prs;
	output wire q;
	output wire q_b;
	
	wire d_b, clk_b;
	wire [5:0] icw; //inter connect wire 
	
	not G1 (d_b,d);
	not G2 (clk_b,clk);
	
	and G3 (icw[0], d, clk_b,ce);
	and G4 (icw[1], d_b, clk_b,ce);
	nor G5 (icw[2], icw[3], icw[0],prs);
	nor G6 (icw[3], icw[2], icw[1],clr); 
	and G7 (icw[4], icw[2], clk);
	and G8 (icw[5], icw[3], clk);
	nor G9 (q, icw[4], q_b);
	nor G10 (q_b, icw[5], q);
	
endmodule

timer_design/dffDesign_pet/src/ms_dff_tb.sv
`timescale 1 us/1 ns 

module ms_dff_tb;
	reg d, clk, prs, clr, ce; //
	wire q, q_b;
	
	ms_dff dut_ms_dff (.d(d),.clk(clk),.clr(clr),.prs(prs),.ce(ce),.q(q),.q_b(q_b)); //,.convention .port(signal) => port is from dut signal is from tb
	
	always begin
		#15.26 clk = ~clk;
	end
	initial begin
		$dumpfile ("dump.vcd");
		$dumpvars(0,ms_dff_tb);
		clk = 0;
		clr = 1;
		prs = 1;
		ce = 0;
		
		$monitor ("clk time= ", $time, "d=%b, clr =%d, q=%b", d,clr,q );
		#14  clr = 1; d = 1; prs =0;
		#14  clr = 0; d = 1; prs =1;
		#14  clr = 1; d = 1;ce =1 ; prs =0;
		#14  d = 1;
		#14 clr = 0 ;
		
		#14  d = 0;
		#14  d = 1;
		#14  d = 0;
		#14  d = 1; clr =1;
		#10	 clr = 0;
		#4   d = 0;
		#14  d = 1;
		
		#14  d = 0;
		#14  d = 1;
		
		#14  d = 0;
		#14  d = 1;
		#14  d = 0;
		#14  d = 1;
		#14  d = 0;
		#14  d = 1;
		#14  d = 0;
		#10 $finish;
	end
		
endmodule

timer_design/dffDesign_pet/dump.vcd
$date
Wed May 24 00:21:58 2023
$end
$version
Aldec HDL Simulator Version 13.0.376
$end
$timescale
1 ns
$end

$scope module ms_dff_tb $end
$var wire 1 ! q $end
$var wire 1 " q_b $end
$var reg 1 # d $end
$var reg 1 $ clk $end
$var reg 1 % prs $end
$var reg 1 & clr $end
$var reg 1 ' ce $end

$scope module dut_ms_dff $end
$var wire 1 ( d $end
$var wire 1 ) clk $end
$var wire 1 * ce $end
$var wire 1 + clr $end
$var wire 1 , prs $end
$var wire 1 ! q $end
$var wire 1 " q_b $end
$var wire 1 - d_b $end
$var wire 1 . clk_b $end
$var wire 6 / icw [5:0] $end
$upscope $end

$upscope $end

$enddefinitions $end
$dumpvars
x!
x"
x#
0$
1%
1&
0'
x(
0)
0*
1+
1,
x-
1.
b0 /
$end
#14000
1#
0%
0,
1(
0-
b100 /
#15260
1$
1)
b10100 /
0.
0!
1"
#28000
0&
1%
1,
0+
b10000 /
b1000 /
b101000 /
0"
1!
#30520
0$
0)
b1000 /
1.
#42000
1&
1'
0%
0,
1*
1+
b1 /
#45780
1$
1)
0.
b0 /
b100 /
b10100 /
0!
1"
#61040
0$
0)
b100 /
1.
b101 /
b1 /
#70000
0&
0+
b1001 /
#76300
1$
1)
b101001 /
0.
b101000 /
0"
1!
#84000
0#
0(
1-
#91560
0$
0)
b1000 /
1.
b1010 /
b10 /
b110 /
#98000
1#
1(
b111 /
0-
b1 /
b1001 /
#106820
1$
1)
b101001 /
0.
b101000 /
#112000
0#
0(
1-
#122080
0$
0)
b1000 /
1.
b1010 /
b10 /
b110 /
#126000
1#
1&
1+
1(
b111 /
0-
b1 /
#136000
0&
0+
b1001 /
#137340
1$
1)
b101001 /
0.
b101000 /
#140000
0#
0(
1-
#152600
0$
0)
b1000 /
1.
b1010 /
b10 /
b110 /
#154000
1#
1(
b111 /
0-
b1 /
b1001 /
#167860
1$
1)
b101001 /
0.
b101000 /
#168000
0#
0(
1-
#182000
1#
1(
0-
#183120
0$
0)
b1000 /
1.
b1001 /
#196000
0#
0(
b1000 /
1-
b1010 /
b10 /
b110 /
#198380
1$
1)
b10110 /
0.
b10100 /
0!
1"
#210000
1#
1(
0-
#213640
0$
0)
b100 /
1.
b101 /
b1 /
b1001 /
#224000
0#
0(
b1000 /
1-
b1010 /
b10 /
b110 /
#228900
1$
1)
b10110 /
0.
b10100 /
#238000
1#
1(
0-
#244160
0$
0)
b100 /
1.
b101 /
b1 /
b1001 /
#252000
0#
0(
b1000 /
1-
b1010 /
b10 /
b110 /
#259420
1$
1)
b10110 /
0.
b10100 /
#266000
1#
1(
0-
#274680
0$
0)
b100 /
1.
b101 /
b1 /
b1001 /
#280000
0#
0(
b1000 /
1-
b1010 /
b10 /
b110 /
#289940
1$
1)
b10110 /
0.
b10100 /
